ansys/mechanical/env/__init__.py
ansys/mechanical/env/mechanical-env
ansys/mechanical/env/run.py
ansys_mechanical_env-0.1.17.data/scripts/mechanical-env
ansys_mechanical_env-0.1.17.dist-info/licenses/LICENSE
ansys_mechanical_env-0.1.17.dist-info/METADATA
ansys_mechanical_env-0.1.17.dist-info/WHEEL
ansys_mechanical_env-0.1.17.dist-info/entry_points.txt
ansys_mechanical_env-0.1.17.dist-info/top_level.txt
ansys_mechanical_env-0.1.17.dist-info/RECORD
