Metadata-Version: 2.4
Name: ansys-mechanical-env
Version: 0.1.17
Summary: A python wrapper for loading environment variables when using PyMechanical embedded instances in Linux.
Home-page: https://github.com/ansys/pymechanical-env
Author: ANSYS, Inc.
Author-email: pyansys.core@ansys.com
Maintainer: ANSYS, Inc.
Maintainer-email: pyansys.core@ansys.com
License: MIT
Classifier: Development Status :: 4 - Beta
Classifier: Programming Language :: Python :: 3
Classifier: License :: OSI Approved :: MIT License
Classifier: Operating System :: POSIX :: Linux
Requires-Python: >=3.10,<4
License-File: LICENSE
Requires-Dist: importlib-metadata>=4.0
Requires-Dist: ansys-tools-path>=0.3.1
Requires-Dist: click>=8.1.3
Dynamic: author
Dynamic: author-email
Dynamic: classifier
Dynamic: description
Dynamic: description-content-type
Dynamic: home-page
Dynamic: license
Dynamic: license-file
Dynamic: maintainer
Dynamic: maintainer-email
Dynamic: requires-dist
Dynamic: requires-python
Dynamic: summary
